python_package_tree.py
python_package_tree-0.0.2.dist-info/METADATA
python_package_tree-0.0.2.dist-info/WHEEL
python_package_tree-0.0.2.dist-info/entry_points.txt
python_package_tree-0.0.2.dist-info/licenses/LICENSE
python_package_tree-0.0.2.dist-info/RECORD
